Ngrok
