Metadata-Version: 2.1
Name: Ngrok.py
Version: 0.167
Summary: My CMD 模組
Home-page: UNKNOWN
License: LGPL
Platform: UNKNOWN
